[
    {
      "pipeline_id": "cd",
      "properties": [
        {
            "name": "change-request-id",
            "type": "text",
            "value": "notAvailable"
        },
        {
            "name": "cluster",
            "type": "text",
            "value": ""
        },
        {
            "name": "cluster-namespace",
            "type": "text",
            "value": "prod"
        },
        {
            "name": "cluster-region",
            "type": "text",
            "value": ""
        },
        {
            "name": "code-signing-certificate",
            "type": "secure",
            "value": ""
        },
        {
            "name": "cos-api-key",
            "type": "secure",
            "value": ""
        },
        {
            "name": "cos-bucket-name",
            "type": "text",
            "value": ""
        },
        {
            "name": "cos-endpoint",
            "type": "text",
            "value": ""
        },
        {
            "name": "doi-environment",
            "type": "text",
            "value": ""
        },
        {
            "name": "doi-ibmcloud-api-key",
            "type": "secure",
            "value": ""
        },
        {
            "name": "doi-toolchain-id",
            "type": "text",
            "value": ""
        },
        {
          "name": "emergency-label",
          "type": "text",
          "value": "EMERGENCY"
        },
        {
            "name": "event-notifications",
            "type": "text",
            "value": "0"
        },
        {
            "name": "force-redeploy",
            "type": "single_select",
            "value": "false",
            "enum": "[false,true]"
        },
        {
          "name": "git-token",
          "type": "secure",
          "value": ""
        },
        {
            "name": "ibmcloud-api-key",
            "type": "secure",
            "value": ""
        },
        {
            "name": "merge-cra-sbom",
            "type": "text",
            "value": "1"
        },
        {
            "name": "peer-review-compliance",
            "type": "text",
            "value": "1"
        },
        {
            "name": "pipeline-config",
            "type": "text",
            "value": ".pipeline-config.yaml"
          },
          {
            "name": "pipeline-config-branch",
            "type": "text",
            "value": ""
          },
        {
            "name": "pipeline-debug",
            "type": "single_select",
            "value": "0",
            "enum": "[0,1]"
        },
        {
            "name": "pre-prod-evidence-collection",
            "type": "text",
            "value": "0"
        },
        {
            "name": "region",
            "type": "text",
            "value": "us-south"
        },
        {
            "name": "satellite-cluster-group",
            "type": "text",
            "value": ""
        },
        {
            "name": "slack-notifications",
            "type": "text",
            "value": "0"
        },
        {
            "name": "source-environment",
            "type": "text",
            "value": "master"
        },
        {
            "name": "target-environment",
            "type": "text",
            "value": "prod"
        },
        {
            "name": "target-environment-detail",
            "type": "text",
            "value": "Production target environment"
        },
        {
            "name": "target-environment-purpose",
            "type": "text",
            "value": "Production target environment"
        },
        {
            "name": "version",
            "type": "text",
            "value": "v1"
        }
      ]
    }
  ]
